reisingerdrive/__init__.py
reisinger_drive-0.2.3.dist-info/METADATA
reisinger_drive-0.2.3.dist-info/WHEEL
reisinger_drive-0.2.3.dist-info/top_level.txt
reisinger_drive-0.2.3.dist-info/RECORD
